pydevkit/__init__.py
pydevkit/argparse.py
pydevkit/conf.py
pydevkit/log/__init__.py
pydevkit/log/base.py
pydevkit/log/config.py
pydevkit/log/extra.py
pydevkit/shell.py
pydevkit/term.py
pydevkit/__version__.py
pydevkit-3.2.2.dist-info/WHEEL
pydevkit-3.2.2.dist-info/METADATA
pydevkit-3.2.2.dist-info/licenses/LICENSE
pydevkit-3.2.2.dist-info/RECORD
