Metadata-Version: 2.1
Name: pydevkit
Version: 3.2.2
Summary: python development kit
Author-email: Anatoly Asviyan <aanatoly@gmail.com>
Classifier: Development Status :: 4 - Beta
Classifier: Environment :: Console
Classifier: Intended Audience :: Developers
Classifier: License :: OSI Approved :: MIT License
Classifier: Operating System :: POSIX
Classifier: Programming Language :: Python :: 3
Classifier: Topic :: Software Development
Project-URL: Homepage, https://github.com/aanatoly/pydevkit
Project-URL: Repository, https://github.com/aanatoly/pydevkit
